Metadata-Version: 2.1
Name: dyvider
Version: 0.2
Summary: Fast and exact partitioning algorithms for graphs embedded in one dimension.
Home-page: https://github.com/jg-you/dyvider
Author: Jean-Gabriel Young, Alice Patania
Author-email: jean-gabriel.young@uvm.edu
License: MIT
Keywords: graphs,community detection,networks,inference
Classifier: Development Status :: 2 - Pre-Alpha  
Classifier: Intended Audience :: Developers
Classifier: Intended Audience :: Science/Research
Classifier: License :: OSI Approved :: MIT License  
Classifier: Operating System :: OS Independent
Classifier: Programming Language :: Python :: 3
Classifier: Topic :: Software Development :: Libraries :: Python Modules
Classifier: Topic :: Scientific/Engineering :: Information Analysis
Classifier: Topic :: Scientific/Engineering :: Mathematics
License-File: LICENSE
